multiomics/__init__.py
multiomics-0.1.dist-info/METADATA
multiomics-0.1.dist-info/WHEEL
multiomics-0.1.dist-info/entry_points.txt
multiomics-0.1.dist-info/license_files/LICENSE.txt
multiomics-0.1.dist-info/RECORD
