Metadata-Version: 2.1
Name: multiomics
Version: 0.1
Summary: Toolbox for multiomics designing in python
Project-URL: Bug Tracker, https://github.com/JinZhangLab/multiomics/issues
Project-URL: Homepage, https://github.com/JinZhangLab/multiomics
Author-email: Jin Zhang <jinzhang@nankai.edu.cn>
Classifier: License :: OSI Approved :: MIT License
Classifier: Operating System :: OS Independent
Classifier: Programming Language :: Python :: 3
Requires-Python: >=3.7
